o2a/__init__.py
o2a/definitions.py
o2a/o2a.py
o2a/converter/__init__.py
o2a/converter/constants.py
o2a/converter/exceptions.py
o2a/converter/mappers.py
o2a/converter/oozie_converter.py
o2a/converter/oozie_node.py
o2a/converter/property_parser.py
o2a/converter/relation.py
o2a/converter/renderers.py
o2a/converter/task.py
o2a/converter/task_group.py
o2a/converter/workflow.py
o2a/converter/workflow_xml_parser.py
o2a/mappers/__init__.py
o2a/mappers/action_mapper.py
o2a/mappers/base_mapper.py
o2a/mappers/decision_mapper.py
o2a/mappers/distcp_mapper.py
o2a/mappers/dummy_mapper.py
o2a/mappers/email_mapper.py
o2a/mappers/end_mapper.py
o2a/mappers/fork_mapper.py
o2a/mappers/fs_mapper.py
o2a/mappers/git_mapper.py
o2a/mappers/hive_mapper.py
o2a/mappers/java_mapper.py
o2a/mappers/join_mapper.py
o2a/mappers/kill_mapper.py
o2a/mappers/mapreduce_mapper.py
o2a/mappers/pig_mapper.py
o2a/mappers/shell_mapper.py
o2a/mappers/spark_mapper.py
o2a/mappers/ssh_mapper.py
o2a/mappers/start_mapper.py
o2a/mappers/subworkflow_mapper.py
o2a/mappers/extensions/prepare_mapper_extension.py
o2a/o2a_libs/__init__.py
o2a/o2a_libs/src/__init__.py
o2a/o2a_libs/src/o2a_lib/__init__.py
o2a/o2a_libs/src/o2a_lib/el_fs_functions.py
o2a/o2a_libs/src/o2a_lib/el_parser.py
o2a/o2a_libs/src/o2a_lib/el_wf_functions.py
o2a/o2a_libs/src/o2a_lib/functions.py
o2a/o2a_libs/src/o2a_lib/property_utils.py
o2a/scripts/git.sh
o2a/scripts/prepare.sh
o2a/templates/dag_body.tpl
o2a/templates/decision.tpl
o2a/templates/distcp.tpl
o2a/templates/dummy.tpl
o2a/templates/email.tpl
o2a/templates/fs_op.tpl
o2a/templates/git.tpl
o2a/templates/git_command.tpl
o2a/templates/hadoop_command.tpl
o2a/templates/hive.tpl
o2a/templates/http.tpl
o2a/templates/http_command.tpl
o2a/templates/java.tpl
o2a/templates/kill.tpl
o2a/templates/mapreduce.tpl
o2a/templates/pig.tpl
o2a/templates/pig_command.tpl
o2a/templates/prepare.tpl
o2a/templates/prepare_command.tpl
o2a/templates/props.tpl
o2a/templates/shell.tpl
o2a/templates/spark.tpl
o2a_acceldata2-2.0.1.dist-info/licenses/LICENSE
o2a_acceldata2-2.0.1.dist-info/METADATA
o2a_acceldata2-2.0.1.dist-info/WHEEL
o2a_acceldata2-2.0.1.dist-info/top_level.txt
o2a_acceldata2-2.0.1.dist-info/RECORD
