Metadata-Version: 2.4
Name: o2a-acceldata2
Version: 2.0.1
Summary: Oozie To Airflow migration tool
Home-page: https://github.com/acceldata-io/o2a
Author: sehaj_@acceldata.io,Jarek Potiuk, Szymon Przedwojski, Kamil Breguła, Feng Lu, Cameron Moberg
Author-email: sehaj@acceldata.io,jarek.potiuk@polidea.com, szymon.przedwojski@polidea.com, kamil.bregula@polidea.com, fenglu@google.com, cjmoberg@google.com
Classifier: Programming Language :: Python :: 3.8
Classifier: Programming Language :: Python :: 3.9
Classifier: Programming Language :: Python :: 3.10
Classifier: Programming Language :: Python :: 3.11
Classifier: License :: OSI Approved :: Apache Software License
Classifier: Operating System :: OS Independent
License-File: LICENSE
Requires-Dist: apache-airflow>=2.8.1
Requires-Dist: autoflake==1.4
Requires-Dist: black==23.1a1
Requires-Dist: flake8==3.8.4
Requires-Dist: google-api-python-client==1.12.11
Requires-Dist: isort==5.7.0
Requires-Dist: j2cli==0.3.10
Requires-Dist: Jinja2==3.1.2
Requires-Dist: lark-parser==0.11.1
Requires-Dist: mypy==1.0.0
Requires-Dist: parameterized==0.7.5
Requires-Dist: paramiko==3.1.0
Requires-Dist: pre-commit==3.3.1
Requires-Dist: pydeps==1.9.13
Requires-Dist: pylint==2.6.0
Requires-Dist: pytest==7.3.1
Requires-Dist: pytest-cov==4.0.0
Requires-Dist: safety==1.10.3
Requires-Dist: sshtunnel==0.4.0
Requires-Dist: twine==4.0.2
Requires-Dist: tzlocal==5.0
Requires-Dist: Werkzeug==2.2.3
Requires-Dist: yamllint==1.31.0
Dynamic: author
Dynamic: author-email
Dynamic: classifier
Dynamic: description
Dynamic: description-content-type
Dynamic: home-page
Dynamic: license-file
Dynamic: requires-dist
Dynamic: summary
